additional_difficulty/__init__.py
additional_difficulty/differences.py
additional_difficulty/division.py
additional_difficulty/factoriser.py
additional_difficulty/products.py
additional_difficulty/py.typed
additional_difficulty/sum_of_two.py
additional_difficulty/text_to_number.py
additional_difficulty-0.0.3.dist-info/METADATA
additional_difficulty-0.0.3.dist-info/WHEEL
additional_difficulty-0.0.3.dist-info/licenses/LICENSE.md
additional_difficulty-0.0.3.dist-info/RECORD
