Metadata-Version: 2.4
Name: additional_difficulty
Version: 0.0.3
Summary: Quantifies the difficulty of mental arithmetic calculations.
Project-URL: Homepage, https://github.com/NumberzGame/Additional_difficulty
Project-URL: Bug Tracker, https://github.com/NumberzGame/Additional_difficulty/issues
Author-email: James Parrott <james.parrott@proton.me>
License: Copyright 2024 James Parrott
License-File: LICENSE.md
Keywords: Education,Mathematics,Mental Arithmetic
Classifier: Programming Language :: Python
Requires-Python: >=3
Provides-Extra: mypy
Requires-Dist: mypy; extra == 'mypy'
Provides-Extra: pyright
Requires-Dist: pyright; extra == 'pyright'
